{
  "GROW_CURVE_ATTACK_304": {
    "1": 1,
    "2": 1.079,
    "3": 1.159,
    "4": 1.238,
    "5": 1.317,
    "6": 1.395,
    "7": 1.474,
    "8": 1.552,
    "9": 1.631,
    "10": 1.709,
    "11": 1.787,
    "12": 1.865,
    "13": 1.942,
    "14": 2.02,
    "15": 2.098,
    "16": 2.175,
    "17": 2.253,
    "18": 2.33,
    "19": 2.408,
    "20": 2.485,
    "21": 2.562,
    "22": 2.639,
    "23": 2.717,
    "24": 2.794,
    "25": 2.871,
    "26": 2.948,
    "27": 3.026,
    "28": 3.103,
    "29": 3.18,
    "30": 3.257,
    "31": 3.334,
    "32": 3.412,
    "33": 3.489,
    "34": 3.566,
    "35": 3.644,
    "36": 3.721,
    "37": 3.798,
    "38": 3.876,
    "39": 3.953,
    "40": 4.031,
    "41": 4.109,
    "42": 4.186,
    "43": 4.264,
    "44": 4.342,
    "45": 4.419,
    "46": 4.497,
    "47": 4.575,
    "48": 4.653,
    "49": 4.731,
    "50": 4.81,
    "51": 4.888,
    "52": 4.966,
    "53": 5.044,
    "54": 5.123,
    "55": 5.201,
    "56": 5.28,
    "57": 5.359,
    "58": 5.437,
    "59": 5.516,
    "60": 5.595,
    "61": 5.674,
    "62": 5.753,
    "63": 5.833,
    "64": 5.912,
    "65": 5.991,
    "66": 6.071,
    "67": 6.15,
    "68": 6.23,
    "69": 6.31,
    "70": 6.39,
    "71": 6.47,
    "72": 6.55,
    "73": 6.63,
    "74": 6.71,
    "75": 6.791,
    "76": 6.871,
    "77": 6.952,
    "78": 7.033,
    "79": 7.113,
    "80": 7.194,
    "81": 7.275,
    "82": 7.357,
    "83": 7.438,
    "84": 7.519,
    "85": 7.601,
    "86": 7.682,
    "87": 7.764,
    "88": 7.846,
    "89": 7.928,
    "90": 8.01
  },
  "GROW_CURVE_ATTACK_301": {
    "1": 1,
    "2": 1.086,
    "3": 1.171,
    "4": 1.257,
    "5": 1.343,
    "6": 1.429,
    "7": 1.516,
    "8": 1.602,
    "9": 1.689,
    "10": 1.775,
    "11": 1.862,
    "12": 1.949,
    "13": 2.036,
    "14": 2.124,
    "15": 2.211,
    "16": 2.299,
    "17": 2.386,
    "18": 2.474,
    "19": 2.562,
    "20": 2.65,
    "21": 2.738,
    "22": 2.827,
    "23": 2.915,
    "24": 3.004,
    "25": 3.093,
    "26": 3.182,
    "27": 3.271,
    "28": 3.36,
    "29": 3.45,
    "30": 3.539,
    "31": 3.629,
    "32": 3.719,
    "33": 3.809,
    "34": 3.899,
    "35": 3.989,
    "36": 4.08,
    "37": 4.17,
    "38": 4.261,
    "39": 4.352,
    "40": 4.443,
    "41": 4.534,
    "42": 4.625,
    "43": 4.717,
    "44": 4.808,
    "45": 4.9,
    "46": 4.992,
    "47": 5.084,
    "48": 5.176,
    "49": 5.268,
    "50": 5.36,
    "51": 5.453,
    "52": 5.546,
    "53": 5.638,
    "54": 5.731,
    "55": 5.825,
    "56": 5.918,
    "57": 6.011,
    "58": 6.105,
    "59": 6.198,
    "60": 6.292,
    "61": 6.386,
    "62": 6.48,
    "63": 6.575,
    "64": 6.669,
    "65": 6.763,
    "66": 6.858,
    "67": 6.953,
    "68": 7.048,
    "69": 7.143,
    "70": 7.238,
    "71": 7.334,
    "72": 7.429,
    "73": 7.525,
    "74": 7.621,
    "75": 7.717,
    "76": 7.813,
    "77": 7.909,
    "78": 8.005,
    "79": 8.102,
    "80": 8.199,
    "81": 8.295,
    "82": 8.392,
    "83": 8.489,
    "84": 8.587,
    "85": 8.684,
    "86": 8.782,
    "87": 8.879,
    "88": 8.977,
    "89": 9.075,
    "90": 9.173
  },
  "GROW_CURVE_ATTACK_302": {
    "1": 1,
    "2": 1.091,
    "3": 1.183,
    "4": 1.275,
    "5": 1.368,
    "6": 1.461,
    "7": 1.554,
    "8": 1.648,
    "9": 1.743,
    "10": 1.837,
    "11": 1.933,
    "12": 2.028,
    "13": 2.124,
    "14": 2.22,
    "15": 2.317,
    "16": 2.414,
    "17": 2.511,
    "18": 2.608,
    "19": 2.706,
    "20": 2.804,
    "21": 2.903,
    "22": 3.002,
    "23": 3.101,
    "24": 3.2,
    "25": 3.3,
    "26": 3.4,
    "27": 3.5,
    "28": 3.601,
    "29": 3.701,
    "30": 3.803,
    "31": 3.904,
    "32": 4.005,
    "33": 4.107,
    "34": 4.209,
    "35": 4.312,
    "36": 4.414,
    "37": 4.517,
    "38": 4.62,
    "39": 4.723,
    "40": 4.827,
    "41": 4.931,
    "42": 5.035,
    "43": 5.139,
    "44": 5.243,
    "45": 5.348,
    "46": 5.453,
    "47": 5.558,
    "48": 5.663,
    "49": 5.768,
    "50": 5.874,
    "51": 5.98,
    "52": 6.086,
    "53": 6.192,
    "54": 6.299,
    "55": 6.406,
    "56": 6.513,
    "57": 6.62,
    "58": 6.727,
    "59": 6.835,
    "60": 6.942,
    "61": 7.05,
    "62": 7.158,
    "63": 7.267,
    "64": 7.375,
    "65": 7.484,
    "66": 7.592,
    "67": 7.701,
    "68": 7.811,
    "69": 7.92,
    "70": 8.03,
    "71": 8.139,
    "72": 8.249,
    "73": 8.359,
    "74": 8.47,
    "75": 8.58,
    "76": 8.691,
    "77": 8.802,
    "78": 8.913,
    "79": 9.024,
    "80": 9.135,
    "81": 9.247,
    "82": 9.358,
    "83": 9.47,
    "84": 9.582,
    "85": 9.694,
    "86": 9.807,
    "87": 9.919,
    "88": 10.032,
    "89": 10.145,
    "90": 10.258
  },
  "GROW_CURVE_ATTACK_303": {
    "1": 1,
    "2": 1.097,
    "3": 1.194,
    "4": 1.292,
    "5": 1.391,
    "6": 1.49,
    "7": 1.59,
    "8": 1.692,
    "9": 1.792,
    "10": 1.895,
    "11": 1.998,
    "12": 2.102,
    "13": 2.206,
    "14": 2.31,
    "15": 2.415,
    "16": 2.521,
    "17": 2.627,
    "18": 2.733,
    "19": 2.841,
    "20": 2.949,
    "21": 3.057,
    "22": 3.165,
    "23": 3.274,
    "24": 3.384,
    "25": 3.493,
    "26": 3.604,
    "27": 3.714,
    "28": 3.825,
    "29": 3.937,
    "30": 4.049,
    "31": 4.161,
    "32": 4.273,
    "33": 4.386,
    "34": 4.5,
    "35": 4.613,
    "36": 4.727,
    "37": 4.841,
    "38": 4.956,
    "39": 5.071,
    "40": 5.186,
    "41": 5.301,
    "42": 5.417,
    "43": 5.533,
    "44": 5.65,
    "45": 5.767,
    "46": 5.884,
    "47": 6,
    "48": 6.118,
    "49": 6.236,
    "50": 6.354,
    "51": 6.473,
    "52": 6.592,
    "53": 6.71,
    "54": 6.83,
    "55": 6.949,
    "56": 7.069,
    "57": 7.19,
    "58": 7.309,
    "59": 7.43,
    "60": 7.55,
    "61": 7.671,
    "62": 7.792,
    "63": 7.913,
    "64": 8.035,
    "65": 8.157,
    "66": 8.279,
    "67": 8.401,
    "68": 8.524,
    "69": 8.646,
    "70": 8.77,
    "71": 8.893,
    "72": 9.016,
    "73": 9.14,
    "74": 9.263,
    "75": 9.387,
    "76": 9.512,
    "77": 9.636,
    "78": 9.761,
    "79": 9.886,
    "80": 10.011,
    "81": 10.136,
    "82": 10.261,
    "83": 10.387,
    "84": 10.513,
    "85": 10.639,
    "86": 10.765,
    "87": 10.892,
    "88": 11.018,
    "89": 11.145,
    "90": 11.272
  }
}